ctbn/__init__.py
ctbn/ctbn.py
ctbn/dump.py
ctbn/graph_preliminaries.py
ctbn/inference.py
ctbn/msa.py
ctbn/parameter_learning_models.py
CTBN-0.0.1.dist-info/LICENSE
CTBN-0.0.1.dist-info/METADATA
CTBN-0.0.1.dist-info/WHEEL
CTBN-0.0.1.dist-info/top_level.txt
CTBN-0.0.1.dist-info/RECORD
