Metadata-Version: 2.1
Name: CTBN
Version: 0.0.1
Summary: Conditional Tree Bayesian Network for multi-label classification
Home-page: https://github.com/brijml/CTBN
Author: Brij Malhotra
Author-email: brij.g.malhotra@gmail.com
License: UNKNOWN
Project-URL: Bug Tracker, https://github.com/pypa/sampleproject/issues
Platform: UNKNOWN
Classifier: Programming Language :: Python :: 3
Classifier: License :: OSI Approved :: MIT License
Classifier: Operating System :: OS Independent
Requires-Python: >=3.6
License-File: LICENSE
Requires-Dist: numpy
Requires-Dist: scikit-learn
